nunet/__init__.py
nunet/base.py
nunet/models.py
nunet_py-0.1.2.dist-info/LICENSE
nunet_py-0.1.2.dist-info/METADATA
nunet_py-0.1.2.dist-info/WHEEL
nunet_py-0.1.2.dist-info/RECORD
