Metadata-Version: 2.1
Name: nunet-py
Version: 0.1.2
Summary: 
Author: Elder Millenial
Author-email: eldermillenial@protonmail.com
Requires-Python: >=3.10,<4.0
Classifier: Programming Language :: Python :: 3
Classifier: Programming Language :: Python :: 3.10
Classifier: Programming Language :: Python :: 3.11
Requires-Dist: pycardano (>=0.10.0,<0.11.0)
Requires-Dist: pydantic (>=2.4.2,<3.0.0)
Requires-Dist: python-dotenv (>=1.0.0,<2.0.0)
Requires-Dist: requests (>=2.31.0,<3.0.0)
Requires-Dist: types-requests (>=2.31.0.10,<3.0.0.0)
Requires-Dist: websockets (>=11.0.3,<12.0.0)
